{
  "expo.jsEngine": "hermes",
  "EX_DEV_CLIENT_NETWORK_INSPECTOR": "true",
  "ios.deploymentTarget": "17.0",
  "expo.inlineModules.watchedDirectories": "[]",
  "expo.inlineModules.xcodeProjectTargets": "{\"mainTarget\":\"Tattvix\",\"targets\":[]}",
  "ios.forceStaticLinking": "[]",
  "apple.extraPods": "[{\"name\":\"GoogleUtilities\",\"modular_headers\":true},{\"name\":\"RecaptchaInterop\",\"modular_headers\":true}]",
  "apple.privacyManifestAggregationEnabled": "true",
  "EXPO_USE_PRECOMPILED_MODULES": "true"
}
